[
  {
    "function": "minecraft:set_lore",
    "lore": [
      {
        "text": "Rare",
        "color": "#9900ff",
        "italic": false
      },
      {
        "text": "+15% Speed",
        "color": "blue",
        "italic": false
      },
      {
        "text": "+5% Armor",
        "color": "blue",
        "italic": false
      },
      {
        "text": "+100% Jump Strength",
        "color": "blue",
        "italic": false
      }
    ],
    "mode": "replace_all"
  },
  {
    "function": "minecraft:set_attributes",
    "modifiers": [
      {
        "id": "b5f23360-4701-4be5-97da-ecc055dbe9df",
        "attribute": "minecraft:generic.movement_speed",
        "amount": 0.015,
        "operation": "add_value",
        "slot": "mainhand"
      },
      {
        "id": "b5f23360-4701-4be5-97da-ecc055dbe9df",
        "attribute": "minecraft:generic.armor",
        "amount": 0.05,
        "operation": "add_multiplied_base",
        "slot": "mainhand"
      },
      {
        "id": "b5f23360-4701-4be5-97da-ecc055dbe9df",
        "attribute": "minecraft:generic.jump_strength",
        "amount": 0.15,
        "operation": "add_value",
        "slot": "mainhand"
      }
    ],
    "replace": true
  },
  {
    "function": "minecraft:set_custom_data",
    "tag": "{modified:1b}"
  },
  {
    "function":"toggle_tooltips",
	"toggles":{"attribute_modifiers":false}}
]



